rangex/__init__.py
rangex-0.0.1.dist-info/LICENSES.txt
rangex-0.0.1.dist-info/METADATA
rangex-0.0.1.dist-info/WHEEL
rangex-0.0.1.dist-info/top_level.txt
rangex-0.0.1.dist-info/RECORD
